mseep_mcp_server_qdrant-0.7.3.dist-info/licenses/LICENSE
tests/__init__.py
tests/test_fastembed_integration.py
tests/test_qdrant_integration.py
tests/test_settings.py
mseep_mcp_server_qdrant-0.7.3.dist-info/METADATA
mseep_mcp_server_qdrant-0.7.3.dist-info/WHEEL
mseep_mcp_server_qdrant-0.7.3.dist-info/entry_points.txt
mseep_mcp_server_qdrant-0.7.3.dist-info/top_level.txt
mseep_mcp_server_qdrant-0.7.3.dist-info/RECORD
