Metadata-Version: 2.4
Name: mseep-mcp-server-qdrant
Version: 0.7.3
Summary: MCP server for retrieving context from a Qdrant vector database
Home-page: 
Author: mseep
Author-email: mseep <support@skydeck.ai>
Maintainer-email: mseep <support@skydeck.ai>
License-Expression: Apache-2.0
Requires-Python: >=3.6
License-File: LICENSE
Requires-Dist: mcp[cli]>=1.3.0
Requires-Dist: fastembed>=0.6.0
Requires-Dist: qdrant-client>=1.12.0
Requires-Dist: pydantic>=2.10.6
Dynamic: author
Dynamic: license-file
Dynamic: requires-python
